tests/__init__.py
tests/test_trace_logger.py
trace_logger/__init__.py
trace_logger/logging_adapter.py
trace_logger/middleware.py
trace_logger/utils.py
api_x_trace_logger-0.0.1.dist-info/LICENSE
api_x_trace_logger-0.0.1.dist-info/METADATA
api_x_trace_logger-0.0.1.dist-info/WHEEL
api_x_trace_logger-0.0.1.dist-info/top_level.txt
api_x_trace_logger-0.0.1.dist-info/RECORD
